helpers/__init__.py
helpers/graphics_widgets.py
helpers/multibar_core.py
helpers/process_handler.py
helpers/util.py
multiprogressbars/__init__.py
multiprogressbars/bar_updater.py
multiprogressbars/example.py
multiprogressbars/multibar.py
multiprogressbars/helpers/__init__.py
multiprogressbars/helpers/graphics_widgets.py
multiprogressbars/helpers/multibar_core.py
multiprogressbars/helpers/process_handler.py
multiprogressbars/helpers/util.py
multiprogressbars-0.1.1.dist-info/LICENSE
multiprogressbars-0.1.1.dist-info/METADATA
multiprogressbars-0.1.1.dist-info/WHEEL
multiprogressbars-0.1.1.dist-info/top_level.txt
multiprogressbars-0.1.1.dist-info/RECORD
