Metadata-Version: 2.1
Name: multiprogressbars
Version: 0.1.1
Summary: A tool for dispatching tasks using multiprocessing, and viewing/controlling live feedback with a GUI array of progress bars.
Home-page: https://github.com/lewisbawden/MultiProgressBars
Author: Lewis Bawden
Author-email: lewisbawden@gmail.com
License: UNKNOWN
Project-URL: GitHub, https://github.com/lewisbawden/MultiProgressBars
Platform: UNKNOWN
Classifier: Programming Language :: Python :: 3
Classifier: Topic :: Utilities
Classifier: Topic :: System :: Monitoring
Requires-Python: >=3.8
